surrealdb2/__init__.py
surrealdb2/http.py
surrealdb2/py.typed
surrealdb2/ws.py
surrealdb2-0.3.2.dist-info/LICENSE
surrealdb2-0.3.2.dist-info/METADATA
surrealdb2-0.3.2.dist-info/WHEEL
surrealdb2-0.3.2.dist-info/RECORD
