Metadata-Version: 2.1
Name: surrealdb2
Version: 0.3.2
Summary: The unofficial SurrealDB library for Python, now working with Pydantic v2.0
Home-page: https://github.com/surrealdb/surrealdb.py
License: Apache-2.0
Keywords: SurrealDB,Database
Author: SurrealDB
Requires-Python: >=3.7,<4.0
Classifier: Development Status :: 4 - Beta
Classifier: Intended Audience :: Developers
Classifier: License :: OSI Approved :: Apache Software License
Classifier: Operating System :: OS Independent
Classifier: Programming Language :: Python :: 3
Classifier: Programming Language :: Python :: 3.7
Classifier: Programming Language :: Python :: 3.8
Classifier: Programming Language :: Python :: 3.9
Classifier: Programming Language :: Python :: 3.10
Classifier: Programming Language :: Python :: 3.11
Classifier: Programming Language :: Python :: 3.12
Classifier: Topic :: Database
Classifier: Topic :: Database :: Front-Ends
Classifier: Topic :: Software Development
Classifier: Topic :: Software Development :: Libraries :: Python Modules
Requires-Dist: httpx (>=0.23.0)
Requires-Dist: pydantic (>=2.0.0)
Requires-Dist: websockets (>=10.4,<11.0)
Project-URL: Documentation, https://surrealdb.com/docs/integration/libraries/python
Project-URL: Repository, https://github.com/surrealdb/surrealdb.py
